xnoxs/__init__.py
xnoxs-0.1.7.dist-info/LICENSE
xnoxs-0.1.7.dist-info/METADATA
xnoxs-0.1.7.dist-info/WHEEL
xnoxs-0.1.7.dist-info/top_level.txt
xnoxs-0.1.7.dist-info/RECORD
