Metadata-Version: 2.1
Name: xnoxs
Version: 0.1.7
Summary: private modul
Author: xnoxs-dev
Author-email: <khaerudin2119@gmail.com>
Keywords: xnoxs
Classifier: Development Status :: 1 - Planning
Classifier: Intended Audience :: Developers
Classifier: Programming Language :: Python
Classifier: Operating System :: Unix
Classifier: Operating System :: MacOS :: MacOS X
Classifier: Operating System :: Microsoft :: Windows
License-File: LICENSE
